mt940_writer.py
mt940_writer-0.8.dist-info/licenses/LICENSE.txt
mt940_writer-0.8.dist-info/METADATA
mt940_writer-0.8.dist-info/WHEEL
mt940_writer-0.8.dist-info/top_level.txt
mt940_writer-0.8.dist-info/RECORD
