Metadata-Version: 2.4
Name: mt940-writer
Version: 0.8
Summary: Writer for MT-940 bank statements
Home-page: https://github.com/ministryofjustice/mt940-writer
Author: Ministry of Justice Digital & Technology
Author-email: dev@digital.justice.gov.uk
License: MIT
Keywords: mt940
Classifier: Development Status :: 4 - Beta
Classifier: Intended Audience :: Developers
Classifier: License :: OSI Approved :: MIT License
Classifier: Natural Language :: English
Classifier: Operating System :: OS Independent
Classifier: Programming Language :: Python :: 3
Classifier: Programming Language :: Python :: 3 :: Only
Classifier: Programming Language :: Python :: 3.10
Classifier: Programming Language :: Python :: 3.11
Classifier: Programming Language :: Python :: 3.12
Classifier: Programming Language :: Python :: 3.13
Classifier: Programming Language :: Python :: 3.14
Classifier: Topic :: Software Development :: Libraries :: Python Modules
Requires-Python: >=3.6
License-File: LICENSE.txt
Dynamic: license-file
